Metadata-Version: 2.1
Name: oneNeuron-pypi.py-chittariraghu
Version: 0.0.1
Summary: its an implementation of perceptron
Home-page: https://github.com/chittariraghu/oneNeuron_pypi.py
Author: USER_NAME
Author-email: chittariraghu@gmail.com
License: UNKNOWN
Project-URL: Bug Tracker, https://github.com/chittariraghu/oneNeuron_pypi.py/issues
Platform: UNKNOWN
Classifier: Programming Language :: Python :: 3
Classifier: License :: OSI Approved :: MIT License
Classifier: Operating System :: OS Independent
Requires-Python: >=3.7
License-File: LICENSE
Requires-Dist: numpy
Requires-Dist: tqdm
